projectstructure/__init__.py
projectstructure/__main__.py
projectstructure/py.typed
projectstructure/utils.py
projectstructure/version.py
project_structure-1.0.1.dist-info/.gitignore
project_structure-1.0.1.dist-info/METADATA
project_structure-1.0.1.dist-info/WHEEL
project_structure-1.0.1.dist-info/entry_points.txt
project_structure-1.0.1.dist-info/top_level.txt
project_structure-1.0.1.dist-info/RECORD
