Metadata-Version: 2.1
Name: project-structure
Version: 1.0.1
Summary: Project structure foundation or template, CLI console scripts.
Home-page: https://gitlab.com/rpatterson/project-structure
Author: Ross Patterson
Author-email: me@rpatterson.net
License: MIT
Keywords: template,structure
Classifier: Development Status :: 4 - Beta
Classifier: Environment :: Console
Classifier: Intended Audience :: Developers
Classifier: Intended Audience :: System Administrators
Classifier: License :: OSI Approved :: MIT License
Classifier: Natural Language :: English
Classifier: Operating System :: OS Independent
Classifier: Programming Language :: Python :: 3
Classifier: Programming Language :: Python :: 3.11
Classifier: Programming Language :: Python :: 3.12
Classifier: Programming Language :: Python :: 3.10
Classifier: Programming Language :: Python :: 3.9
Classifier: Programming Language :: Python :: 3.8
Classifier: Programming Language :: Python :: 3 :: Only
Classifier: Topic :: Utilities
Requires-Python: >=3.8
Requires-Dist: argcomplete
Provides-Extra: devel
Requires-Dist: prospector[with_everything] ; extra == 'devel'
Requires-Dist: xenon ; extra == 'devel'
Requires-Dist: black ; extra == 'devel'
Requires-Dist: autoflake ; extra == 'devel'
Requires-Dist: autopep8 ; extra == 'devel'
Requires-Dist: build ; extra == 'devel'
Provides-Extra: test
Requires-Dist: pytest ; extra == 'test'
Requires-Dist: coverage ; extra == 'test'
Requires-Dist: pip-tools ; extra == 'test'
